<?xml version="1.0" encoding="utf-8"?>
<!--Generated by crowdin.net-->
<resources>
  <string name="msg_unknown_error_body">Παρουσιάστηκε άγνωστο σφάλμα. Παρακαλώ ελέγξτε τη σύνδεση δικτύου και προσπαθήστε ξανά.</string>
  <string name="msg_failed_to_parse_api_response">Αδυναμία ανάλυσης της απάντησης του API. Παρακαλώ ξαναπροσπαθήστε. Εάν το πρόβλημα εμμένει, παρακαλώ επικοινωνήστε μαζί μας για βοήθεια.</string>
  <string name="msg_no_api_response">Το API δεν επέστρεψε καμία απάντηση. Παρακαλώ ξαναπροσπαθήστε. Εάν το πρόβλημα εμμένει, παρακαλώ επικοινωνήστε μαζί μας για βοήθεια.</string>
  <string name="journey_distance_imperial_fmt">%s μίλια</string>
  <string name="journey_distance_metrics_fmt">%s km</string>
</resources>
